[
    {
        "close_date": "2026-05-22",
        "ticker": "BSX",
        "entry_date": "2026-05-20",
        "entry_price": 56.608,
        "exit_price": 58.09,
        "usd_invested": 3.9998,
        "usd_returned": 2.0523,
        "pnl_usd": -1.9475,
        "pnl_pct": -48.69,
        "outcome": "loss",
        "predicting_models": [
            "llama3.1:8b-instruct-q8_0",
            "gemma4",
            "mistral-nemo"
        ],
        "consensus_buy_high": 56.61,
        "consensus_sell_low": 58.09
    },
    {
        "close_date": "2026-05-22",
        "ticker": "CPNG",
        "entry_date": "2026-05-21",
        "entry_price": 15.438,
        "exit_price": 16.05,
        "usd_invested": 3.9764,
        "usd_returned": 2.067,
        "pnl_usd": -1.9094,
        "pnl_pct": -48.02,
        "outcome": "loss",
        "predicting_models": [
            "llama3.1:8b-instruct-q8_0",
            "gemma4",
            "mistral-nemo"
        ],
        "consensus_buy_high": 15.53,
        "consensus_sell_low": 16.05
    },
    {
        "close_date": "2026-05-22",
        "ticker": "LYFT",
        "entry_date": "2026-05-21",
        "entry_price": 13.17,
        "exit_price": 13.85,
        "usd_invested": 4.0,
        "usd_returned": 2.1033,
        "pnl_usd": -1.8967,
        "pnl_pct": -47.42,
        "outcome": "loss",
        "predicting_models": [
            "llama3.1:8b-instruct-q8_0",
            "gemma4",
            "mistral-nemo"
        ],
        "consensus_buy_high": 13.17,
        "consensus_sell_low": 13.85
    },
    {
        "close_date": "2026-05-22",
        "ticker": "ZETA",
        "entry_date": "2026-05-21",
        "entry_price": 17.808,
        "exit_price": 18.872,
        "usd_invested": 3.929,
        "usd_returned": 2.0818,
        "pnl_usd": -1.8472,
        "pnl_pct": -47.01,
        "outcome": "loss",
        "predicting_models": [
            "llama3.1:8b-instruct-q8_0",
            "gemma4",
            "mistral-nemo"
        ],
        "consensus_buy_high": 18.13,
        "consensus_sell_low": 18.87
    },
    {
        "close_date": "2026-05-22",
        "ticker": "PATH",
        "entry_date": "2026-05-21",
        "entry_price": 10.358,
        "exit_price": 11.02,
        "usd_invested": 3.8794,
        "usd_returned": 2.0637,
        "pnl_usd": -1.8157,
        "pnl_pct": -46.8,
        "outcome": "loss",
        "predicting_models": [
            "llama3.1:8b-instruct-q8_0",
            "gemma4",
            "mistral-nemo"
        ],
        "consensus_buy_high": 10.68,
        "consensus_sell_low": 11.02
    },
    {
        "close_date": "2026-05-22",
        "ticker": "PINS",
        "entry_date": "2026-05-21",
        "entry_price": 18.698,
        "exit_price": 19.23,
        "usd_invested": 3.9678,
        "usd_returned": 2.0403,
        "pnl_usd": -1.9275,
        "pnl_pct": -48.58,
        "outcome": "loss",
        "predicting_models": [
            "llama3.1:8b-instruct-q8_0",
            "gemma4",
            "mistral-nemo"
        ],
        "consensus_buy_high": 18.85,
        "consensus_sell_low": 19.23
    },
    {
        "close_date": "2026-05-22",
        "ticker": "TQQQ",
        "entry_date": "2026-05-21",
        "entry_price": 75.418,
        "exit_price": 78.034,
        "usd_invested": 3.9868,
        "usd_returned": 2.0625,
        "pnl_usd": -1.9243,
        "pnl_pct": -48.27,
        "outcome": "loss",
        "predicting_models": [
            "llama3.1:8b-instruct-q8_0",
            "gemma4",
            "mistral-nemo"
        ],
        "consensus_buy_high": 75.67,
        "consensus_sell_low": 78.0
    },
    {
        "close_date": "2026-05-22",
        "ticker": "AMAT",
        "entry_date": "2026-05-21",
        "entry_price": 423.162,
        "exit_price": 434.342,
        "usd_invested": 3.9922,
        "usd_returned": 2.0488,
        "pnl_usd": -1.9434,
        "pnl_pct": -48.68,
        "outcome": "loss",
        "predicting_models": [
            "llama3.1:8b-instruct-q8_0",
            "gemma4",
            "mistral-nemo"
        ],
        "consensus_buy_high": 424.0,
        "consensus_sell_low": 434.33
    },
    {
        "close_date": "2026-05-22",
        "ticker": "AAL",
        "entry_date": "2026-05-21",
        "entry_price": 12.97,
        "exit_price": 13.686,
        "usd_invested": 4.0,
        "usd_returned": 2.1104,
        "pnl_usd": -1.8896,
        "pnl_pct": -47.24,
        "outcome": "loss",
        "predicting_models": [
            "llama3.1:8b-instruct-q8_0",
            "gemma4",
            "mistral-nemo"
        ],
        "consensus_buy_high": 12.97,
        "consensus_sell_low": 13.15
    }
]